machine_learning_evaluation/__init__.py
machine_learning_evaluation/model_evaluation.py
machine_learning_evaluation-1.1.4.dist-info/LICENSE.txt
machine_learning_evaluation-1.1.4.dist-info/METADATA
machine_learning_evaluation-1.1.4.dist-info/WHEEL
machine_learning_evaluation-1.1.4.dist-info/top_level.txt
machine_learning_evaluation-1.1.4.dist-info/RECORD
