Metadata-Version: 2.1
Name: machine_learning_evaluation
Version: 1.1.4
Summary: A library for evaluating machine learning models.
Author: Jay Dhotre
Author-email: jaydhotre524@gmail.com
License: MIT
Classifier: Development Status :: 5 - Production/Stable
Classifier: Intended Audience :: Developers
Classifier: License :: OSI Approved :: MIT License
Classifier: Programming Language :: Python :: 3
Classifier: Programming Language :: Python :: 3.6
Classifier: Programming Language :: Python :: 3.7
Classifier: Programming Language :: Python :: 3.8
Classifier: Programming Language :: Python :: 3.9
Classifier: Operating System :: OS Independent
License-File: LICENSE.txt
Requires-Dist: scikit-learn (>=0.24.0)
Requires-Dist: pandas
Requires-Dist: numpy
Requires-Dist: imblearn
